fetchify.py
fetchify-2.1.0.dist-info/METADATA
fetchify-2.1.0.dist-info/WHEEL
fetchify-2.1.0.dist-info/top_level.txt
fetchify-2.1.0.dist-info/RECORD
