Metadata-Version: 2.1
Name: fetchify
Version: 2.1.0
Summary: Library to access Code Files from Cloud
Home-page: https://techinfoak.wixsite.com/tech-info
Author: Anupam Kanoongo
Author-email: programmer.tiak@gmail.com
License: MIT
Project-URL: Our Website, https://techinfoak.wixsite.com/devak
Project-URL: Our YT Handle, https://youtube.com/@developer.anupam
Classifier: Programming Language :: Python :: 3
Classifier: License :: OSI Approved :: MIT License
Classifier: Operating System :: OS Independent
Requires-Python: >=3.6
Requires-Dist: requests
Requires-Dist: google-generativeai
